{"type": "FeatureCollection", "features": [{"feature_map": {"fmap": [{"type": "Feature", "properties": {"id": 545, "title": "456"}, "geometry": {"type": "Point", "coordinates": ["76.9797914", "9.8497872"]}}]}}, {"feature_map": {"fmap": [{"type": "Feature", "properties": {"id": 9909, "title": "hexa"}, "geometry": {"type": "Point", "coordinates": [-83.1137366, 32.3293809]}}]}}, {"feature_map": {"fmap": [{"type": "Feature", "properties": {"id": 12345, "title": "termind"}, "geometry": {"type": "Point", "coordinates": ["-0.1276474", "51.5073219"]}}]}}, {"feature_map": {"fmap": [{"type": "Feature", "properties": {"id": 46532, "title": "jaijai"}, "geometry": {"type": "Point", "coordinates": ["76.9628425", "11.0018115"]}}]}}, {"feature_map": {"fmap": [{"type": "Feature", "properties": {"id": 90990, "title": "jerri"}, "geometry": {"type": "Point", "coordinates": ["-0.1276474", "51.5073219"]}}]}}, {"feature_map": {"fmap": [{"type": "Feature", "properties": {"id": 99898, "title": "grd"}, "geometry": {"type": "Point", "coordinates": ["-0.1276474", "51.5073219"]}}]}}, {"feature_map": {"fmap": [{"type": "Feature", "properties": {"id": 876500, "title": "gooday"}, "geometry": {"type": "Point", "coordinates": ["76.9628425", "11.0018115"]}}]}}, {"feature_map": {"fmap": [{"type": "Feature", "properties": {"id": 9988777, "title": "Testjson"}, "geometry": {"type": "Point", "coordinates": ["46.4416422", "-18.9249604"]}}]}}, {"feature_map": {"fmap": [{"type": "Feature", "properties": {"id": 98888890, "title": "meh"}, "geometry": {"type": "Point", "coordinates": ["91.2999102", "25.5379432"]}}]}}]}